eqnlint/__init__.py
eqnlint/bin/__init__.py
eqnlint/bin/audit_template.py
eqnlint/bin/citation_audit.py
eqnlint/bin/context_audit.py
eqnlint/bin/create_submission.py
eqnlint/bin/dimensional_audit.py
eqnlint/bin/eqnlint.py
eqnlint/bin/opacity_audit.py
eqnlint/bin/prose_audit.py
eqnlint/bin/symbolic_audit.py
eqnlint/bin/units_audit.py
eqnlint/lib/__init__.py
eqnlint/lib/_ai.py
eqnlint/lib/_budget.py
eqnlint/lib/_cli.py
eqnlint/lib/_debug.py
eqnlint/lib/_extract.py
eqnlint/lib/_fewshots.py
eqnlint/lib/_textio.py
eqnlint-0.2.5.dist-info/licenses/LICENSE
eqnlint-0.2.5.dist-info/METADATA
eqnlint-0.2.5.dist-info/WHEEL
eqnlint-0.2.5.dist-info/entry_points.txt
eqnlint-0.2.5.dist-info/top_level.txt
eqnlint-0.2.5.dist-info/RECORD
