Metadata-Version: 2.4
Name: eqnlint
Version: 0.2.5
Summary: Audits LaTeX papers for units, dimensions, symbols, citations, context, opacity, and prose.
Author-email: John Ryan <tambotitree@gmail.com>
License-Expression: MIT
Project-URL: Homepage, https://github.com/tambotitree/eqnlint-project
Project-URL: Issues, https://github.com/tambotitree/eqnlint-project/issues
Keywords: latex,audit,linter,units,dimensions,citations,prose
Classifier: Programming Language :: Python :: 3
Classifier: Operating System :: OS Independent
Classifier: Topic :: Text Processing :: Markup :: LaTeX
Classifier: Intended Audience :: Science/Research
Classifier: Development Status :: 4 - Beta
Requires-Python: >=3.9
License-File: LICENSE
Requires-Dist: openai
Requires-Dist: sympy
Requires-Dist: tqdm
Requires-Dist: rich
Requires-Dist: python-dotenv
Dynamic: license-file
